jupyterlab_polus_render/__init__.py
jupyterlab_polus_render/_frontend.py
jupyterlab_polus_render/_version.py
jupyterlab_polus_render/handlers.py
jupyterlab_polus_render/render.py
jupyterlab_polus_render/labextension/package.json
jupyterlab_polus_render/labextension/static/122.3be7638fdd123cfe081f.js
jupyterlab_polus_render/labextension/static/227.68aed46569fe18401c29.js
jupyterlab_polus_render/labextension/static/227.68aed46569fe18401c29.js.LICENSE.txt
jupyterlab_polus_render/labextension/static/285.5e764e4155c3275578cb.js
jupyterlab_polus_render/labextension/static/285.5e764e4155c3275578cb.js.LICENSE.txt
jupyterlab_polus_render/labextension/static/359.7f6dcf75b8dac8108799.js
jupyterlab_polus_render/labextension/static/501.128f3cca45f259356cd3.js
jupyterlab_polus_render/labextension/static/501.128f3cca45f259356cd3.js.LICENSE.txt
jupyterlab_polus_render/labextension/static/509.03a69eab877004c42e01.js
jupyterlab_polus_render/labextension/static/563.0f78313e7ba40f04be46.js
jupyterlab_polus_render/labextension/static/574.c56b3d0e2b33f2396646.js
jupyterlab_polus_render/labextension/static/665.43d3ab6083cfaeef23a4.js
jupyterlab_polus_render/labextension/static/778.db9385935611d6411a63.js
jupyterlab_polus_render/labextension/static/811.b8ea280b183a962acd74.js
jupyterlab_polus_render/labextension/static/895.4925b5772d35cdb0722d.js
jupyterlab_polus_render/labextension/static/943.9edb4058fc9ac473ed45.js
jupyterlab_polus_render/labextension/static/961.070096ddc26d2e1b9c63.js
jupyterlab_polus_render/labextension/static/remoteEntry.dd5a371026c79f77b0e0.js
jupyterlab_polus_render/labextension/static/style.js
jupyterlab_polus_render/labextension/static/third-party-licenses.json
jupyterlab_polus_render/nbextension/extension.js
jupyterlab_polus_render/nbextension/index.js
jupyterlab_polus_render/nbextension/index.js.LICENSE.txt
jupyterlab_polus_render/nbextension/index.js.map
jupyterlab_polus_render-1.0.1.data/data/etc/jupyter/jupyter_server_config.d/jupyterlab_polus_render.json
jupyterlab_polus_render-1.0.1.dist-info/METADATA
jupyterlab_polus_render-1.0.1.dist-info/WHEEL
jupyterlab_polus_render-1.0.1.dist-info/licenses/LICENSE.txt
jupyterlab_polus_render-1.0.1.dist-info/RECORD
